{
  "generatedAt": "2026-04-01T22:00:08.361494+00:00",
  "sources": [
    "https://store.steampowered.com/feeds/news/app/2868840/",
    "https://www.megacrit.com/news",
    "https://www.reddit.com/r/slaythespire/new/.rss",
    "https://www.reddit.com/search.rss?q=slay%20the%20spire%202&sort=new"
  ],
  "items": [
    {
      "source": "steam_news",
      "title": "Slay the Spire: The Board Game — Downfall Expansion Kickstarter Live",
      "url": "https://store.steampowered.com/news/app/2868840/view/503978984819656657",
      "publishedAt": "Tue, 24 Mar 2026 17:33:57 +0000",
      "observedAt": "2026-04-13T22:00:02.980343+00:00",
      "summary": "The Kickstarter for Downfall, an official expansion to Slay the Spire: The Board Game inspired by a community mod, is now live."
    },
    {
      "source": "steam_news",
      "title": "The Neowsletter — March 2026",
      "url": "https://store.steampowered.com/news/app/2868840/view/502852451136700526",
      "publishedAt": "Fri, 13 Mar 2026 21:49:33 +0000",
      "observedAt": "2026-04-13T22:00:02.983664+00:00",
      "summary": "Mega Crit's March Neowsletter thanks the community for launch feedback and shares the team's early reactions."
    },
    {
      "source": "steam_news",
      "title": "Patch Notes — Beta v0.99",
      "url": "https://store.steampowered.com/news/app/2868840/view/502852451136700758",
      "publishedAt": "Fri, 13 Mar 2026 00:42:32 +0000",
      "observedAt": "2026-04-13T22:00:02.984229+00:00",
      "summary": "Patch v0.99 includes bug fixes, art updates, and a new max-HP cap; rollout begins on selected platforms."
    },
    {
      "source": "megacrit_news",
      "title": "Release Date Trailer",
      "url": "https://www.megacrit.com/news/2026-02-19-release-date-trailer/",
      "publishedAt": null,
      "observedAt": "2026-04-13T22:00:07.156594+00:00",
      "summary": "Mega Crit published the official release-date trailer for Slay the Spire 2."
    },
    {
      "source": "megacrit_news",
      "title": "Just Announced — Slay the Spire 2",
      "url": "https://www.megacrit.com/news/2024-04-15-just-announced-slay-the-spire-2-copy/",
      "publishedAt": null,
      "observedAt": "2026-04-13T22:00:07.156955+00:00",
      "summary": "Mega Crit's original announcement post for Slay the Spire 2."
    },
    {
      "source": "megacrit_news",
      "title": "Youtooz x Slay the Spire — Limited Figures",
      "url": "https://www.megacrit.com/news/2024-03-12-youtooz-x-slay-the-spire-limited-edition-figures-out-now/",
      "publishedAt": null,
      "observedAt": "2026-04-13T22:00:07.156988+00:00",
      "summary": "Mega Crit posted about the Youtooz limited-edition Slay the Spire figures release."
    }
  ],
  "highlights": [
    {
      "kind": "megacrit_news",
      "item": {
        "source": "megacrit_news",
        "title": "Release Date Trailer",
        "url": "https://www.megacrit.com/news/2026-02-19-release-date-trailer/",
        "publishedAt": null,
        "observedAt": "2026-04-13T22:00:07.156594+00:00",
        "summary": "Mega Crit published the official release-date trailer for Slay the Spire 2."
      }
    },
    {
      "kind": "steam_news",
      "item": {
        "source": "steam_news",
        "title": "Slay the Spire: The Board Game — Downfall Expansion Kickstarter Live",
        "url": "https://store.steampowered.com/news/app/2868840/view/503978984819656657",
        "publishedAt": "Tue, 24 Mar 2026 17:33:57 +0000",
        "observedAt": "2026-04-13T22:00:02.980343+00:00",
        "summary": "The Kickstarter for Downfall, an official expansion to Slay the Spire: The Board Game inspired by a community mod, is now live."
      }
    }
  ]
}
